didyou/__init__.py
didyou/constants.py
didyou/mean.py
didyou/utils.py
didyou-0.1.0.dist-info/WHEEL
didyou-0.1.0.dist-info/METADATA
didyou-0.1.0.dist-info/RECORD
